ebmeta/__init__.py
ebmeta/cli.py
ebmeta/model.py
ebmeta-1.0.5.dist-info/LICENSE
ebmeta-1.0.5.dist-info/METADATA
ebmeta-1.0.5.dist-info/WHEEL
ebmeta-1.0.5.dist-info/entry_points.txt
ebmeta-1.0.5.dist-info/top_level.txt
ebmeta-1.0.5.dist-info/RECORD
